{
  "zonesCrossNominees": [
    [
      {
        "inZone": [
          true,
          false
        ],
        "crossingPair": [
          {
            "time": "2016-01-07T01:51:59Z",
            "lat": -33.36241667,
            "fix": 12,
            "lng": 147.93645,
            "alt": 414
          },
          {
            "time": "2016-01-07T01:52:04Z",
            "lat": -33.3625,
            "fix": 13,
            "lng": 147.93723333,
            "alt": 431
          }
        ]
      },
      {
        "inZone": [
          false,
          true
        ],
        "crossingPair": [
          {
            "time": "2016-01-07T01:58:14Z",
            "lat": -33.3638,
            "fix": 87,
            "lng": 147.93708333,
            "alt": 907
          },
          {
            "time": "2016-01-07T01:58:19Z",
            "lat": -33.36306667,
            "fix": 88,
            "lng": 147.93661667,
            "alt": 915
          }
        ]
      },
      {
        "inZone": [
          true,
          false
        ],
        "crossingPair": [
          {
            "time": "2016-01-07T01:58:19Z",
            "lat": -33.36306667,
            "fix": 88,
            "lng": 147.93661667,
            "alt": 915
          },
          {
            "time": "2016-01-07T01:58:24Z",
            "lat": -33.36246667,
            "fix": 89,
            "lng": 147.93705,
            "alt": 922
          }
        ]
      },
      {
        "inZone": [
          false,
          true
        ],
        "crossingPair": [
          {
            "time": "2016-01-07T01:59:44Z",
            "lat": -33.36263333,
            "fix": 105,
            "lng": 147.93755,
            "alt": 904
          },
          {
            "time": "2016-01-07T01:59:49Z",
            "lat": -33.36265,
            "fix": 106,
            "lng": 147.93675,
            "alt": 898
          }
        ]
      },
      {
        "inZone": [
          true,
          false
        ],
        "crossingPair": [
          {
            "time": "2016-01-07T02:01:34Z",
            "lat": -33.35721667,
            "fix": 127,
            "lng": 147.93048333,
            "alt": 984
          },
          {
            "time": "2016-01-07T02:01:39Z",
            "lat": -33.35645,
            "fix": 128,
            "lng": 147.93021667,
            "alt": 980
          }
        ]
      }
    ],
    [
      {
        "inZone": [
          true,
          false
        ],
        "crossingPair": [
          {
            "time": "2016-01-07T02:28:44Z",
            "lat": -33.27303333,
            "fix": 453,
            "lng": 147.90955,
            "alt": 1823
          },
          {
            "time": "2016-01-07T02:28:49Z",
            "lat": -33.27191667,
            "fix": 454,
            "lng": 147.91003333,
            "alt": 1813
          }
        ]
      }
    ],
    []
  ],
  "zonesCrossExcluded": [],
  "startSelected": null,
  "zonesCrossSelected": [
    {
      "inZone": [
        true,
        false
      ],
      "crossingPair": [
        {
          "time": "2016-01-07T01:51:59Z",
          "lat": -33.36241667,
          "fix": 12,
          "lng": 147.93645,
          "alt": 414
        },
        {
          "time": "2016-01-07T01:52:04Z",
          "lat": -33.3625,
          "fix": 13,
          "lng": 147.93723333,
          "alt": 431
        }
      ]
    },
    {
      "inZone": [
        true,
        false
      ],
      "crossingPair": [
        {
          "time": "2016-01-07T02:28:44Z",
          "lat": -33.27303333,
          "fix": 453,
          "lng": 147.90955,
          "alt": 1823
        },
        {
          "time": "2016-01-07T02:28:49Z",
          "lat": -33.27191667,
          "fix": 454,
          "lng": 147.91003333,
          "alt": 1813
        }
      ]
    },
    null
  ],
  "startNominees": []
}
