[
  {
    "inter": {
      "time": "2016-01-09T01:57:38.371513227842Z",
      "lat": -33.35683287,
      "fixFrac": 215.18575661392148,
      "lng": 147.92940882,
      "alt": 381.81
    },
    "cross": {
      "inZone": [
        false,
        true
      ],
      "crossingPair": [
        {
          "time": "2016-01-09T01:57:38Z",
          "lat": -33.35678333,
          "fix": 215,
          "lng": 147.92935,
          "alt": 382
        },
        {
          "time": "2016-01-09T01:57:40Z",
          "lat": -33.35705,
          "fix": 216,
          "lng": 147.92966667,
          "alt": 381
        }
      ]
    }
  },
  null,
  null,
  null,
  null,
  null
]
