{
  "zonesCrossNominees": [
    [
      {
        "inZone": [
          false,
          true
        ],
        "crossingPair": [
          {
            "time": "2016-01-08T02:06:59Z",
            "lat": -33.35635,
            "fix": 63,
            "lng": 147.93368333,
            "alt": 0
          },
          {
            "time": "2016-01-08T02:07:02Z",
            "lat": -33.3565,
            "fix": 64,
            "lng": 147.93318333,
            "alt": 0
          }
        ]
      },
      {
        "inZone": [
          true,
          false
        ],
        "crossingPair": [
          {
            "time": "2016-01-08T02:07:38Z",
            "lat": -33.35921667,
            "fix": 76,
            "lng": 147.92725,
            "alt": 0
          },
          {
            "time": "2016-01-08T02:07:41Z",
            "lat": -33.35946667,
            "fix": 77,
            "lng": 147.92676667,
            "alt": 0
          }
        ]
      },
      {
        "inZone": [
          false,
          true
        ],
        "crossingPair": [
          {
            "time": "2016-01-08T02:09:08Z",
            "lat": -33.35821667,
            "fix": 106,
            "lng": 147.92698333,
            "alt": 0
          },
          {
            "time": "2016-01-08T02:09:11Z",
            "lat": -33.35866667,
            "fix": 107,
            "lng": 147.92745,
            "alt": 0
          }
        ]
      },
      {
        "inZone": [
          true,
          false
        ],
        "crossingPair": [
          {
            "time": "2016-01-08T02:09:47Z",
            "lat": -33.35645,
            "fix": 119,
            "lng": 147.93101667,
            "alt": 0
          },
          {
            "time": "2016-01-08T02:09:50Z",
            "lat": -33.35608333,
            "fix": 120,
            "lng": 147.93086667,
            "alt": 0
          }
        ]
      }
    ],
    [
      {
        "inZone": [
          true,
          false
        ],
        "crossingPair": [
          {
            "time": "2016-01-08T03:15:44Z",
            "lat": -33.29293333,
            "fix": 1438,
            "lng": 148.00276667,
            "alt": 0
          },
          {
            "time": "2016-01-08T03:15:47Z",
            "lat": -33.2926,
            "fix": 1439,
            "lng": 148.00313333,
            "alt": 0
          }
        ]
      }
    ],
    [
      {
        "inZone": [
          false,
          true
        ],
        "crossingPair": [
          {
            "time": "2016-01-08T04:45:50Z",
            "lat": -32.76085,
            "fix": 3240,
            "lng": 148.64498333,
            "alt": 0
          },
          {
            "time": "2016-01-08T04:45:53Z",
            "lat": -32.76073333,
            "fix": 3241,
            "lng": 148.64566667,
            "alt": 0
          }
        ]
      },
      {
        "inZone": [
          true,
          false
        ],
        "crossingPair": [
          {
            "time": "2016-01-08T04:48:05Z",
            "lat": -32.75941667,
            "fix": 3285,
            "lng": 148.6531,
            "alt": 0
          },
          {
            "time": "2016-01-08T04:48:08Z",
            "lat": -32.75951667,
            "fix": 3286,
            "lng": 148.65371667,
            "alt": 0
          }
        ]
      }
    ],
    []
  ],
  "zonesCrossExcluded": [],
  "startSelected": [
    "2016-01-08T03:15:00Z",
    {
      "inZone": [
        true,
        false
      ],
      "crossingPair": [
        {
          "time": "2016-01-08T03:15:44Z",
          "lat": -33.29293333,
          "fix": 1438,
          "lng": 148.00276667,
          "alt": 0
        },
        {
          "time": "2016-01-08T03:15:47Z",
          "lat": -33.2926,
          "fix": 1439,
          "lng": 148.00313333,
          "alt": 0
        }
      ]
    }
  ],
  "zonesCrossSelected": [
    {
      "inZone": [
        false,
        true
      ],
      "crossingPair": [
        {
          "time": "2016-01-08T02:06:59Z",
          "lat": -33.35635,
          "fix": 63,
          "lng": 147.93368333,
          "alt": 0
        },
        {
          "time": "2016-01-08T02:07:02Z",
          "lat": -33.3565,
          "fix": 64,
          "lng": 147.93318333,
          "alt": 0
        }
      ]
    },
    {
      "inZone": [
        true,
        false
      ],
      "crossingPair": [
        {
          "time": "2016-01-08T03:15:44Z",
          "lat": -33.29293333,
          "fix": 1438,
          "lng": 148.00276667,
          "alt": 0
        },
        {
          "time": "2016-01-08T03:15:47Z",
          "lat": -33.2926,
          "fix": 1439,
          "lng": 148.00313333,
          "alt": 0
        }
      ]
    },
    {
      "inZone": [
        false,
        true
      ],
      "crossingPair": [
        {
          "time": "2016-01-08T04:45:50Z",
          "lat": -32.76085,
          "fix": 3240,
          "lng": 148.64498333,
          "alt": 0
        },
        {
          "time": "2016-01-08T04:45:53Z",
          "lat": -32.76073333,
          "fix": 3241,
          "lng": 148.64566667,
          "alt": 0
        }
      ]
    },
    null
  ],
  "startNominees": [
    [
      "2016-01-08T04:00:00Z",
      []
    ],
    [
      "2016-01-08T03:45:00Z",
      []
    ],
    [
      "2016-01-08T03:30:00Z",
      []
    ],
    [
      "2016-01-08T03:15:00Z",
      [
        {
          "inZone": [
            true,
            false
          ],
          "crossingPair": [
            {
              "time": "2016-01-08T03:15:44Z",
              "lat": -33.29293333,
              "fix": 1438,
              "lng": 148.00276667,
              "alt": 0
            },
            {
              "time": "2016-01-08T03:15:47Z",
              "lat": -33.2926,
              "fix": 1439,
              "lng": 148.00313333,
              "alt": 0
            }
          ]
        }
      ]
    ]
  ]
}
