[
  {
    "inter": {
      "time": "2016-01-02T02:55:11.011477383807Z",
      "lat": -33.35643486,
      "fixFrac": 56.01147738380789,
      "lng": 147.93340019,
      "alt": 260.02
    },
    "cross": {
      "inZone": [
        false,
        true
      ],
      "crossingPair": [
        {
          "time": "2016-01-02T02:55:11Z",
          "lat": -33.35643333,
          "fix": 56,
          "lng": 147.9334,
          "alt": 260
        },
        {
          "time": "2016-01-02T02:55:12Z",
          "lat": -33.35656667,
          "fix": 57,
          "lng": 147.93341667,
          "alt": 262
        }
      ]
    }
  },
  {
    "inter": {
      "time": "2016-01-02T03:17:27.257501763378Z",
      "lat": -33.33222375,
      "fixFrac": 1392.2575017633785,
      "lng": 147.89009142,
      "alt": 672
    },
    "cross": {
      "inZone": [
        true,
        false
      ],
      "crossingPair": [
        {
          "time": "2016-01-02T03:17:27Z",
          "lat": -33.33226667,
          "fix": 1392,
          "lng": 147.8901,
          "alt": 672
        },
        {
          "time": "2016-01-02T03:17:28Z",
          "lat": -33.3321,
          "fix": 1393,
          "lng": 147.89006667,
          "alt": 672
        }
      ]
    }
  },
  null,
  null,
  null,
  null
]
