{
  "zonesCrossNominees": [
    [
      {
        "inZone": [
          false,
          true
        ],
        "crossingPair": [
          {
            "time": "2016-01-06T02:41:12Z",
            "lat": -33.35631667,
            "fix": 228,
            "lng": 147.93331667,
            "alt": 0
          },
          {
            "time": "2016-01-06T02:41:15Z",
            "lat": -33.35655,
            "fix": 229,
            "lng": 147.9336,
            "alt": 0
          }
        ]
      },
      {
        "inZone": [
          true,
          false
        ],
        "crossingPair": [
          {
            "time": "2016-01-06T02:42:00Z",
            "lat": -33.3602,
            "fix": 244,
            "lng": 147.93721667,
            "alt": 0
          },
          {
            "time": "2016-01-06T02:42:03Z",
            "lat": -33.36038333,
            "fix": 245,
            "lng": 147.93756667,
            "alt": 0
          }
        ]
      }
    ],
    [
      {
        "inZone": [
          true,
          false
        ],
        "crossingPair": [
          {
            "time": "2016-01-06T02:54:51Z",
            "lat": -33.27341667,
            "fix": 501,
            "lng": 147.90483333,
            "alt": 0
          },
          {
            "time": "2016-01-06T02:54:54Z",
            "lat": -33.27275,
            "fix": 502,
            "lng": 147.9046,
            "alt": 0
          }
        ]
      }
    ],
    [
      {
        "inZone": [
          false,
          true
        ],
        "crossingPair": [
          {
            "time": "2016-01-06T05:26:50Z",
            "lat": -31.9471,
            "fix": 3540,
            "lng": 147.20668333,
            "alt": 0
          },
          {
            "time": "2016-01-06T05:26:53Z",
            "lat": -31.94615,
            "fix": 3541,
            "lng": 147.20648333,
            "alt": 0
          }
        ]
      }
    ]
  ],
  "zonesCrossExcluded": [],
  "startSelected": null,
  "zonesCrossSelected": [
    {
      "inZone": [
        false,
        true
      ],
      "crossingPair": [
        {
          "time": "2016-01-06T02:41:12Z",
          "lat": -33.35631667,
          "fix": 228,
          "lng": 147.93331667,
          "alt": 0
        },
        {
          "time": "2016-01-06T02:41:15Z",
          "lat": -33.35655,
          "fix": 229,
          "lng": 147.9336,
          "alt": 0
        }
      ]
    },
    {
      "inZone": [
        true,
        false
      ],
      "crossingPair": [
        {
          "time": "2016-01-06T02:54:51Z",
          "lat": -33.27341667,
          "fix": 501,
          "lng": 147.90483333,
          "alt": 0
        },
        {
          "time": "2016-01-06T02:54:54Z",
          "lat": -33.27275,
          "fix": 502,
          "lng": 147.9046,
          "alt": 0
        }
      ]
    },
    {
      "inZone": [
        false,
        true
      ],
      "crossingPair": [
        {
          "time": "2016-01-06T05:26:50Z",
          "lat": -31.9471,
          "fix": 3540,
          "lng": 147.20668333,
          "alt": 0
        },
        {
          "time": "2016-01-06T05:26:53Z",
          "lat": -31.94615,
          "fix": 3541,
          "lng": 147.20648333,
          "alt": 0
        }
      ]
    }
  ],
  "startNominees": []
}
