{
  "zonesCrossNominees": [
    [],
    [
      {
        "inZone": [
          true,
          false
        ],
        "crossingPair": [
          {
            "time": "2016-01-06T02:22:45Z",
            "lat": -33.2721,
            "fix": 204,
            "lng": 147.91568333,
            "alt": 1797
          },
          {
            "time": "2016-01-06T02:22:50Z",
            "lat": -33.27123333,
            "fix": 205,
            "lng": 147.91586667,
            "alt": 1792
          }
        ]
      },
      {
        "inZone": [
          false,
          true
        ],
        "crossingPair": [
          {
            "time": "2016-01-06T02:23:40Z",
            "lat": -33.2709,
            "fix": 215,
            "lng": 147.91685,
            "alt": 1793
          },
          {
            "time": "2016-01-06T02:23:45Z",
            "lat": -33.27136667,
            "fix": 216,
            "lng": 147.9166,
            "alt": 1787
          }
        ]
      },
      {
        "inZone": [
          true,
          false
        ],
        "crossingPair": [
          {
            "time": "2016-01-06T02:23:50Z",
            "lat": -33.27155,
            "fix": 217,
            "lng": 147.91565,
            "alt": 1777
          },
          {
            "time": "2016-01-06T02:23:55Z",
            "lat": -33.27125,
            "fix": 218,
            "lng": 147.91445,
            "alt": 1766
          }
        ]
      }
    ],
    [
      {
        "inZone": [
          false,
          true
        ],
        "crossingPair": [
          {
            "time": "2016-01-06T04:57:51Z",
            "lat": -31.9476,
            "fix": 2059,
            "lng": 147.20723333,
            "alt": 372
          },
          {
            "time": "2016-01-06T04:57:56Z",
            "lat": -31.94616667,
            "fix": 2060,
            "lng": 147.20673333,
            "alt": 354
          }
        ]
      }
    ]
  ],
  "zonesCrossExcluded": [],
  "startSelected": null,
  "zonesCrossSelected": [
    null,
    {
      "inZone": [
        true,
        false
      ],
      "crossingPair": [
        {
          "time": "2016-01-06T02:23:50Z",
          "lat": -33.27155,
          "fix": 217,
          "lng": 147.91565,
          "alt": 1777
        },
        {
          "time": "2016-01-06T02:23:55Z",
          "lat": -33.27125,
          "fix": 218,
          "lng": 147.91445,
          "alt": 1766
        }
      ]
    },
    {
      "inZone": [
        false,
        true
      ],
      "crossingPair": [
        {
          "time": "2016-01-06T04:57:51Z",
          "lat": -31.9476,
          "fix": 2059,
          "lng": 147.20723333,
          "alt": 372
        },
        {
          "time": "2016-01-06T04:57:56Z",
          "lat": -31.94616667,
          "fix": 2060,
          "lng": 147.20673333,
          "alt": 354
        }
      ]
    }
  ],
  "startNominees": []
}
