{
  "zonesCrossNominees": [
    [
      {
        "inZone": [
          false,
          true
        ],
        "crossingPair": [
          {
            "time": "2016-01-06T01:58:31Z",
            "lat": -33.35631667,
            "fix": 249,
            "lng": 147.93353333,
            "alt": 0
          },
          {
            "time": "2016-01-06T01:58:34Z",
            "lat": -33.35663333,
            "fix": 250,
            "lng": 147.93373333,
            "alt": 0
          }
        ]
      },
      {
        "inZone": [
          true,
          false
        ],
        "crossingPair": [
          {
            "time": "2016-01-06T01:59:34Z",
            "lat": -33.36243333,
            "fix": 270,
            "lng": 147.9369,
            "alt": 0
          },
          {
            "time": "2016-01-06T01:59:37Z",
            "lat": -33.36271667,
            "fix": 271,
            "lng": 147.937,
            "alt": 0
          }
        ]
      },
      {
        "inZone": [
          false,
          true
        ],
        "crossingPair": [
          {
            "time": "2016-01-06T02:00:55Z",
            "lat": -33.35715,
            "fix": 297,
            "lng": 147.9352,
            "alt": 0
          },
          {
            "time": "2016-01-06T02:00:58Z",
            "lat": -33.3573,
            "fix": 298,
            "lng": 147.93505,
            "alt": 0
          }
        ]
      },
      {
        "inZone": [
          true,
          false
        ],
        "crossingPair": [
          {
            "time": "2016-01-06T02:01:01Z",
            "lat": -33.35743333,
            "fix": 299,
            "lng": 147.93526667,
            "alt": 0
          },
          {
            "time": "2016-01-06T02:01:04Z",
            "lat": -33.35738333,
            "fix": 300,
            "lng": 147.93555,
            "alt": 0
          }
        ]
      }
    ],
    [
      {
        "inZone": [
          true,
          false
        ],
        "crossingPair": [
          {
            "time": "2016-01-06T02:15:52Z",
            "lat": -33.27725,
            "fix": 596,
            "lng": 147.89085,
            "alt": 0
          },
          {
            "time": "2016-01-06T02:15:55Z",
            "lat": -33.27668333,
            "fix": 597,
            "lng": 147.8907,
            "alt": 0
          }
        ]
      },
      {
        "inZone": [
          false,
          true
        ],
        "crossingPair": [
          {
            "time": "2016-01-06T02:18:22Z",
            "lat": -33.2772,
            "fix": 646,
            "lng": 147.89058333,
            "alt": 0
          },
          {
            "time": "2016-01-06T02:18:25Z",
            "lat": -33.2774,
            "fix": 647,
            "lng": 147.89085,
            "alt": 0
          }
        ]
      },
      {
        "inZone": [
          true,
          false
        ],
        "crossingPair": [
          {
            "time": "2016-01-06T02:18:40Z",
            "lat": -33.27785,
            "fix": 652,
            "lng": 147.89026667,
            "alt": 0
          },
          {
            "time": "2016-01-06T02:18:43Z",
            "lat": -33.27725,
            "fix": 653,
            "lng": 147.88975,
            "alt": 0
          }
        ]
      }
    ],
    []
  ],
  "zonesCrossExcluded": [],
  "startSelected": null,
  "zonesCrossSelected": [
    {
      "inZone": [
        false,
        true
      ],
      "crossingPair": [
        {
          "time": "2016-01-06T01:58:31Z",
          "lat": -33.35631667,
          "fix": 249,
          "lng": 147.93353333,
          "alt": 0
        },
        {
          "time": "2016-01-06T01:58:34Z",
          "lat": -33.35663333,
          "fix": 250,
          "lng": 147.93373333,
          "alt": 0
        }
      ]
    },
    {
      "inZone": [
        true,
        false
      ],
      "crossingPair": [
        {
          "time": "2016-01-06T02:18:40Z",
          "lat": -33.27785,
          "fix": 652,
          "lng": 147.89026667,
          "alt": 0
        },
        {
          "time": "2016-01-06T02:18:43Z",
          "lat": -33.27725,
          "fix": 653,
          "lng": 147.88975,
          "alt": 0
        }
      ]
    },
    null
  ],
  "startNominees": []
}
