[
  {
    "inter": {
      "time": "2016-01-03T01:44:30.46507262834Z",
      "lat": -33.3619938,
      "fixFrac": 22.24650726283444,
      "lng": 147.93721846,
      "alt": 766.04
    },
    "cross": {
      "inZone": [
        false,
        true
      ],
      "crossingPair": [
        {
          "time": "2016-01-03T01:44:28Z",
          "lat": -33.36185,
          "fix": 22,
          "lng": 147.93793333,
          "alt": 751
        },
        {
          "time": "2016-01-03T01:44:38Z",
          "lat": -33.36243333,
          "fix": 23,
          "lng": 147.93503333,
          "alt": 812
        }
      ]
    }
  },
  {
    "inter": {
      "time": "2016-01-03T02:04:50.36378570733Z",
      "lat": -33.36201186,
      "fixFrac": 144.0363785707339,
      "lng": 147.82379633,
      "alt": 1532.29
    },
    "cross": {
      "inZone": [
        true,
        false
      ],
      "crossingPair": [
        {
          "time": "2016-01-03T02:04:50Z",
          "lat": -33.36201667,
          "fix": 144,
          "lng": 147.82386667,
          "alt": 1532
        },
        {
          "time": "2016-01-03T02:05:00Z",
          "lat": -33.36188333,
          "fix": 145,
          "lng": 147.82193333,
          "alt": 1540
        }
      ]
    }
  },
  {
    "inter": {
      "time": "2016-01-03T02:48:40.582893934988Z",
      "lat": -33.42831569,
      "fixFrac": 406.86096464499644,
      "lng": 147.51963574,
      "alt": 1452.97
    },
    "cross": {
      "inZone": [
        false,
        true
      ],
      "crossingPair": [
        {
          "time": "2016-01-03T02:48:38Z",
          "lat": -33.428,
          "fix": 406,
          "lng": 147.52016667,
          "alt": 1459
        },
        {
          "time": "2016-01-03T02:48:41Z",
          "lat": -33.42836667,
          "fix": 407,
          "lng": 147.51955,
          "alt": 1452
        }
      ]
    }
  },
  {
    "inter": {
      "time": "2016-01-03T04:23:07.916839213824Z",
      "lat": -33.44695974,
      "fixFrac": 973.8452627448323,
      "lng": 146.72547457,
      "alt": 654.62
    },
    "cross": {
      "inZone": [
        false,
        true
      ],
      "crossingPair": [
        {
          "time": "2016-01-03T04:23:02Z",
          "lat": -33.44646667,
          "fix": 973,
          "lng": 146.72688333,
          "alt": 658
        },
        {
          "time": "2016-01-03T04:23:09Z",
          "lat": -33.44705,
          "fix": 974,
          "lng": 146.72521667,
          "alt": 654
        }
      ]
    }
  }
]
